Metadata-Version: 2.1
Name: briefstats
Version: 0.0.3
Summary: A brief statistics tool for Chinese.
Home-page: UNKNOWN
Author: Kang Zhou
Author-email: zkSpongeBob@126.com
Maintainer: Kang Zhou
Maintainer-email: zkSpongeBob@126.com
License: MIT License
Platform: all
License-File: LICENSE
